[
  {
    "user_id": 1025,
    "login": "akzhan",
    "password": "93mqxcxim8",
    "app_role": "Владелец",
    "fio": "Akzhan",
    "main_role_code": "ADM"
  },
  {
    "user_id": 1064,
    "login": "amir.bayzhanovich",
    "password": "se03o18h4q",
    "app_role": "Владелец",
    "fio": "Амир Байжанович",
    "main_role_code": "ADM"
  },
  {
    "user_id": 1250,
    "login": "manager",
    "password": "7kf8ticjfz",
    "app_role": "Менеджер",
    "fio": "Manager",
    "main_role_code": ""
  },
  {
    "user_id": 1036,
    "login": "adilkhan.esov",
    "password": "53q8bavykw",
    "app_role": "Менеджер",
    "fio": "Адильхан Есов",
    "main_role_code": "BChefB"
  },
  {
    "user_id": 1042,
    "login": "aydar.zhunusov",
    "password": "zhkw09v34l",
    "app_role": "Менеджер",
    "fio": "Айдар Жунусов",
    "main_role_code": "MN1"
  },
  {
    "user_id": 1069,
    "login": "andrey.skoryatin",
    "password": "671i25c9v4",
    "app_role": "Менеджер",
    "fio": "Андрей Скорятин",
    "main_role_code": "HR"
  },
  {
    "user_id": 1071,
    "login": "ardana.serikkyzy",
    "password": "fogayuijvf",
    "app_role": "Менеджер",
    "fio": "Ардана Сериккызы",
    "main_role_code": "MN0"
  },
  {
    "user_id": 1074,
    "login": "asel.moldakulova",
    "password": "6m0usbppkr",
    "app_role": "Менеджер",
    "fio": "Асель Молдакулова",
    "main_role_code": "MN1"
  },
  {
    "user_id": 1078,
    "login": "aslan.zhaysanov",
    "password": "i30liw8ka4",
    "app_role": "Менеджер",
    "fio": "Аслан Жайсанов",
    "main_role_code": "MN1"
  },
  {
    "user_id": 1263,
    "login": "gabit.kaspaev",
    "password": "co7hgv83pi",
    "app_role": "Менеджер",
    "fio": "Габит Каспаев",
    "main_role_code": "MN1"
  },
  {
    "user_id": 1117,
    "login": "dias.musin",
    "password": "mx8hb3mki4",
    "app_role": "Менеджер",
    "fio": "Диас Мусин",
    "main_role_code": "MN1"
  },
  {
    "user_id": 1125,
    "login": "ekaterina.turikovich",
    "password": "0nbl0gpmr1",
    "app_role": "Менеджер",
    "fio": "Екатерина Турикович",
    "main_role_code": "MN1"
  },
  {
    "user_id": 1129,
    "login": "erlan.ablashimov",
    "password": "hncb6ndpub",
    "app_role": "Менеджер",
    "fio": "Ерлан Аблашимов",
    "main_role_code": "MN1"
  },
  {
    "user_id": 1130,
    "login": "erlan.esenmuratov",
    "password": "7q30fqdxje",
    "app_role": "Менеджер",
    "fio": "Ерлан Есенмуратов",
    "main_role_code": "MN1"
  },
  {
    "user_id": 1133,
    "login": "zhanar.karibaeva",
    "password": "w47gci581d",
    "app_role": "Менеджер",
    "fio": "Жанар Карибаева",
    "main_role_code": "buh"
  },
  {
    "user_id": 1251,
    "login": "kenzhegul.gl.bukh",
    "password": "fhi9kwhqkb",
    "app_role": "Менеджер",
    "fio": "Кенжегул Гл Бух",
    "main_role_code": "GBuh"
  },
  {
    "user_id": 1156,
    "login": "maksim.rabkanov.upravlyayushchiy",
    "password": "uso2hipke9",
    "app_role": "Менеджер",
    "fio": "Максим Рабканов Управляющий",
    "main_role_code": "MN0"
  },
  {
    "user_id": 1165,
    "login": "mila.ganbarova",
    "password": "lq1m0a1uoi",
    "app_role": "Менеджер",
    "fio": "Мила Ганбарова",
    "main_role_code": "GuestM"
  },
  {
    "user_id": 1246,
    "login": "polatqozha.abdulla",
    "password": "h7u5cdq6x3",
    "app_role": "Менеджер",
    "fio": "Полатқожа Абдулла",
    "main_role_code": "MN1"
  },
  {
    "user_id": 1202,
    "login": "rustem.baytursynov",
    "password": "gs2tb5arjx",
    "app_role": "Менеджер",
    "fio": "Рустем Байтурсынов",
    "main_role_code": "MN1"
  },
  {
    "user_id": 1226,
    "login": "timur.basha",
    "password": "nzxn0l1s7c",
    "app_role": "Менеджер",
    "fio": "Тимур Баша",
    "main_role_code": "MN1"
  },
  {
    "user_id": 1228,
    "login": "tulegen.baetov",
    "password": "8sascz2f5s",
    "app_role": "Менеджер",
    "fio": "Тулеген Баетов",
    "main_role_code": "TekhD"
  },
  {
    "user_id": 1243,
    "login": "yana.pobedonostseva",
    "password": "r83az21us5",
    "app_role": "Менеджер",
    "fio": "Яна Победоносцева",
    "main_role_code": "BChef"
  },
  {
    "user_id": 1027,
    "login": "it-.spetsialist",
    "password": "kgx9gb1nx7",
    "app_role": "Официант",
    "fio": "IT- специалист",
    "main_role_code": "KWAAKA"
  },
  {
    "user_id": 1029,
    "login": "abdulaziz.khaydaraliev",
    "password": "5ljkfzsi9v",
    "app_role": "Официант",
    "fio": "Абдулазиз Хайдаралиев",
    "main_role_code": "PoV"
  },
  {
    "user_id": 1030,
    "login": "abdurakhimov.baurzhan",
    "password": "axjfmsv4kt",
    "app_role": "Официант",
    "fio": "Абдурахимов Бауржан",
    "main_role_code": "PoV"
  },
  {
    "user_id": 1031,
    "login": "abzal.dzhumagaliev",
    "password": "mg7p3fphdp",
    "app_role": "Официант",
    "fio": "Абзал Джумагалиев",
    "main_role_code": "GorCeh"
  },
  {
    "user_id": 1032,
    "login": "abylay.baytobet",
    "password": "9bgyznp659",
    "app_role": "Официант",
    "fio": "Абылай Байтобет",
    "main_role_code": "Sous chef"
  },
  {
    "user_id": 1033,
    "login": "abylay.orazov",
    "password": "bt3vewyfwv",
    "app_role": "Официант",
    "fio": "Абылай Оразов",
    "main_role_code": "PoV"
  },
  {
    "user_id": 1034,
    "login": "abylaykhan.zholdasbek",
    "password": "y9krvzegiz",
    "app_role": "Официант",
    "fio": "Абылайхан Жолдасбек",
    "main_role_code": "WR1"
  },
  {
    "user_id": 1035,
    "login": "adel.bazarbaeva",
    "password": "8jxzq2q9id",
    "app_role": "Официант",
    "fio": "Адель Базарбаева",
    "main_role_code": "WR1"
  },
  {
    "user_id": 1038,
    "login": "azat.abdukarimov",
    "password": "54henowyyf",
    "app_role": "Официант",
    "fio": "Азат Абдукаримов",
    "main_role_code": "VTech"
  },
  {
    "user_id": 1039,
    "login": "azimzhan.kaldybaev",
    "password": "h2haygs7nl",
    "app_role": "Официант",
    "fio": "Азимжан Калдыбаев",
    "main_role_code": "Myas"
  },
  {
    "user_id": 1040,
    "login": "aybol.toregeldiev",
    "password": "1yr7r482w2",
    "app_role": "Официант",
    "fio": "Айбол Торегелдиев",
    "main_role_code": "SG1"
  },
  {
    "user_id": 1041,
    "login": "aygerim.zhusupova",
    "password": "1k59qi6ixc",
    "app_role": "Официант",
    "fio": "Айгерим Жусупова",
    "main_role_code": "Lepka"
  },
  {
    "user_id": 1252,
    "login": "aygul.turebekova",
    "password": "6vzazgig9r",
    "app_role": "Официант",
    "fio": "Айгуль Туребекова",
    "main_role_code": "Lepka"
  },
  {
    "user_id": 1257,
    "login": "aygul.uskenova",
    "password": "selpkhqwyj",
    "app_role": "Официант",
    "fio": "Айгуль Ускенова",
    "main_role_code": "PoV"
  },
  {
    "user_id": 1043,
    "login": "aydos.zhumakhmetov",
    "password": "a8f59tet25",
    "app_role": "Официант",
    "fio": "Айдос Жумахметов",
    "main_role_code": "WR1"
  },
  {
    "user_id": 1044,
    "login": "ayzhan.amirali",
    "password": "7l16klbrt7",
    "app_role": "Официант",
    "fio": "Айжан Амирали",
    "main_role_code": "Testo"
  },
  {
    "user_id": 1273,
    "login": "aynur.bazarbaeva",
    "password": "zu6d1py06o",
    "app_role": "Официант",
    "fio": "Айнур Базарбаева",
    "main_role_code": "WR1"
  },
  {
    "user_id": 1045,
    "login": "aynur.bayzhanova",
    "password": "8ichfbb5e7",
    "app_role": "Официант",
    "fio": "Айнур Байжанова",
    "main_role_code": "Calc"
  },
  {
    "user_id": 1046,
    "login": "akmarzhan.saktaganova",
    "password": "0uwb1h7vs8",
    "app_role": "Официант",
    "fio": "Акмаржан Сактаганова",
    "main_role_code": "WR1"
  },
  {
    "user_id": 1047,
    "login": "aknazar.aysauyt",
    "password": "6g1ilpy5if",
    "app_role": "Официант",
    "fio": "Акназар Айсауыт",
    "main_role_code": "WR1"
  },
  {
    "user_id": 1048,
    "login": "aleksandr.kim",
    "password": "i1fb87w8q3",
    "app_role": "Официант",
    "fio": "Александр Ким",
    "main_role_code": "WR1"
  },
  {
    "user_id": 1049,
    "login": "aleksandra.utkina",
    "password": "8cwnr0n9ok",
    "app_role": "Официант",
    "fio": "Александра Уткина",
    "main_role_code": "Calc"
  },
  {
    "user_id": 1050,
    "login": "aliev.ravil",
    "password": "9wjn5xi2z2",
    "app_role": "Официант",
    "fio": "Алиев Равиль",
    "main_role_code": "WR1"
  },
  {
    "user_id": 1051,
    "login": "alima.guzerbaeva",
    "password": "mwvdu2tqko",
    "app_role": "Официант",
    "fio": "Алима Гузербаева",
    "main_role_code": "PoV"
  },
  {
    "user_id": 1052,
    "login": "alimov.nikolay",
    "password": "slf696ald1",
    "app_role": "Официант",
    "fio": "Алимов Николай",
    "main_role_code": "MN1"
  },
  {
    "user_id": 1277,
    "login": "alinur.abishev",
    "password": "jivsh8f7lv",
    "app_role": "Официант",
    "fio": "Алинур Абишев",
    "main_role_code": "BR1"
  },
  {
    "user_id": 1053,
    "login": "alisher.baylenov",
    "password": "vitkpatg49",
    "app_role": "Официант",
    "fio": "Алишер Байленов",
    "main_role_code": "WR1"
  },
  {
    "user_id": 1054,
    "login": "alisher.rysbaev",
    "password": "phebxy3hml",
    "app_role": "Официант",
    "fio": "Алишер Рысбаев",
    "main_role_code": "Testo"
  },
  {
    "user_id": 1055,
    "login": "aliya.makhmetova",
    "password": "r06dtv5itv",
    "app_role": "Официант",
    "fio": "Алия Махметова",
    "main_role_code": "GBuh"
  },
  {
    "user_id": 1056,
    "login": "almas.muratov",
    "password": "cofpps8waf",
    "app_role": "Официант",
    "fio": "Алмас Муратов",
    "main_role_code": "WR1"
  },
  {
    "user_id": 1057,
    "login": "almat.zhaksylykov",
    "password": "t2akqrgdcd",
    "app_role": "Официант",
    "fio": "Алмат Жаксылыков",
    "main_role_code": "Sous chef"
  },
  {
    "user_id": 1058,
    "login": "altynay.zhidebaeva",
    "password": "zw4os3x8vs",
    "app_role": "Официант",
    "fio": "Алтынай Жидебаева",
    "main_role_code": "WR1"
  },
  {
    "user_id": 1059,
    "login": "alaziz.turar",
    "password": "pym1dlu2iq",
    "app_role": "Официант",
    "fio": "Альазиз Тұрар",
    "main_role_code": "BR1"
  },
  {
    "user_id": 1060,
    "login": "almira.karataeva",
    "password": "50m9vnll2g",
    "app_role": "Официант",
    "fio": "Альмира Каратаева",
    "main_role_code": "PoV"
  },
  {
    "user_id": 1061,
    "login": "alnazar.zakir",
    "password": "3s9k1h7sfg",
    "app_role": "Официант",
    "fio": "Альназар Закир",
    "main_role_code": "WR1"
  },
  {
    "user_id": 1062,
    "login": "amina.bekmurzina",
    "password": "zqbve4zt9z",
    "app_role": "Официант",
    "fio": "Амина Бекмурзина",
    "main_role_code": "WR1"
  },
  {
    "user_id": 1063,
    "login": "amindzhoni.negmatzoda",
    "password": "wjcsxny6o3",
    "app_role": "Официант",
    "fio": "Аминджони Негматзода",
    "main_role_code": "PoV"
  },
  {
    "user_id": 1065,
    "login": "amir.bolatov",
    "password": "8n47v9qio8",
    "app_role": "Официант",
    "fio": "Амир Болатов",
    "main_role_code": "PoV"
  },
  {
    "user_id": 1066,
    "login": "amira.amre",
    "password": "oi3lamrzsa",
    "app_role": "Официант",
    "fio": "Амира Әмре",
    "main_role_code": "Mark"
  },
  {
    "user_id": 1067,
    "login": "anastasiya.dzhusupova",
    "password": "2vx99hr2ov",
    "app_role": "Официант",
    "fio": "Анастасия Джусупова",
    "main_role_code": "Mark"
  },
  {
    "user_id": 1068,
    "login": "andrey.kornev",
    "password": "5i0cenahal",
    "app_role": "Официант",
    "fio": "Андрей Корнев",
    "main_role_code": "WR1"
  },
  {
    "user_id": 1274,
    "login": "ansar.olzhabekov",
    "password": "4kar8gcn5l",
    "app_role": "Официант",
    "fio": "Ансар Олжабеков",
    "main_role_code": "WR1"
  },
  {
    "user_id": 1070,
    "login": "ardak.kappasov",
    "password": "jcylgyxlxe",
    "app_role": "Официант",
    "fio": "Ардак Каппасов",
    "main_role_code": "PoV"
  },
  {
    "user_id": 1072,
    "login": "arman.dzhensekbaev",
    "password": "7e6b2h88rq",
    "app_role": "Официант",
    "fio": "Арман Дженсекбаев",
    "main_role_code": "Teh"
  },
  {
    "user_id": 1073,
    "login": "asel.taylakova",
    "password": "ydvei1mg3x",
    "app_role": "Официант",
    "fio": "Асел Тайлакова",
    "main_role_code": "PoV"
  },
  {
    "user_id": 1075,
    "login": "asiya.abisheva",
    "password": "btd7ldse3s",
    "app_role": "Официант",
    "fio": "Асия Абишева",
    "main_role_code": "GorCeh"
  },
  {
    "user_id": 1076,
    "login": "asiya.nazarova",
    "password": "afk0vju648",
    "app_role": "Официант",
    "fio": "Асия Назарова",
    "main_role_code": "PoV"
  },
  {
    "user_id": 1077,
    "login": "askerbay.orazbekov",
    "password": "gutkz7uymc",
    "app_role": "Официант",
    "fio": "Аскербай Оразбеков",
    "main_role_code": "GC"
  },
  {
    "user_id": 1269,
    "login": "askhat.saylaukenov",
    "password": "fqztxryzbh",
    "app_role": "Официант",
    "fio": "Асхат Сайлаукенов",
    "main_role_code": "Myas"
  },
  {
    "user_id": 1079,
    "login": "asylbek.meyramov",
    "password": "jxt6kzkym6",
    "app_role": "Официант",
    "fio": "Асылбек Мейрамов",
    "main_role_code": "WR1"
  },
  {
    "user_id": 1080,
    "login": "atikullo.madamidov",
    "password": "6itsjn75iz",
    "app_role": "Официант",
    "fio": "Атикулло Мадамидов",
    "main_role_code": "PoV"
  },
  {
    "user_id": 1081,
    "login": "ashimkhan.tleuberde",
    "password": "zhck4d7zq6",
    "app_role": "Официант",
    "fio": "Ашимхан Тлеуберде",
    "main_role_code": "BR1"
  },
  {
    "user_id": 1082,
    "login": "aqerke.oraq",
    "password": "hdt3n2s5he",
    "app_role": "Официант",
    "fio": "Ақерке Орақ",
    "main_role_code": "WR1"
  },
  {
    "user_id": 1083,
    "login": "babazhanov.dilrukh",
    "password": "0v6ecz02xh",
    "app_role": "Официант",
    "fio": "Бабажанов Дилрух",
    "main_role_code": "Sous chef"
  },
  {
    "user_id": 1084,
    "login": "bagila.bisenova",
    "password": "vjcho4bc8b",
    "app_role": "Официант",
    "fio": "Багила Бисенова",
    "main_role_code": "PoV"
  },
  {
    "user_id": 1085,
    "login": "bakdaulet.zhaksybay",
    "password": "xtwc78mtpi",
    "app_role": "Официант",
    "fio": "Бакдаулет Жаксыбай",
    "main_role_code": "BR1"
  },
  {
    "user_id": 1086,
    "login": "bauyrzhan.abishev",
    "password": "fj877lovkn",
    "app_role": "Официант",
    "fio": "Бауыржан Абишев",
    "main_role_code": "BR1"
  },
  {
    "user_id": 1087,
    "login": "bauyrzhan.saurikov",
    "password": "04z3ub4765",
    "app_role": "Официант",
    "fio": "Бауыржан Сауриков",
    "main_role_code": "PoV"
  },
  {
    "user_id": 1088,
    "login": "bauyrzhan.qaydarov",
    "password": "fota3t6oar",
    "app_role": "Официант",
    "fio": "Бауыржан Қайдаров",
    "main_role_code": "BR1"
  },
  {
    "user_id": 1089,
    "login": "bakhtier.bakhtovari",
    "password": "xb5asus961",
    "app_role": "Официант",
    "fio": "Бахтиер Бахтовари",
    "main_role_code": "Fas"
  },
  {
    "user_id": 1090,
    "login": "baqdaulet.ayaghan",
    "password": "n0dhgx1jl0",
    "app_role": "Официант",
    "fio": "Бақдәулет Аяған",
    "main_role_code": "WR1"
  },
  {
    "user_id": 1091,
    "login": "beysenbay.ulzhalgas",
    "password": "2t5uldvdbo",
    "app_role": "Официант",
    "fio": "Бейсенбай Улжалгас",
    "main_role_code": "WR1"
  },
  {
    "user_id": 1092,
    "login": "bekarys.alikulov",
    "password": "oekx8pnmgs",
    "app_role": "Официант",
    "fio": "Бекарыс Аликулов",
    "main_role_code": "PoV"
  },
  {
    "user_id": 1271,
    "login": "bekbolat.batyraliev",
    "password": "b8f2l85rsh",
    "app_role": "Официант",
    "fio": "Бекболат Батыралиев",
    "main_role_code": "WR1"
  },
  {
    "user_id": 1093,
    "login": "bekzat.zhandeldy",
    "password": "vqj7ozdswu",
    "app_role": "Официант",
    "fio": "Бекзат Жанделды",
    "main_role_code": "WR1"
  },
  {
    "user_id": 1094,
    "login": "bekzat.tuzelov",
    "password": "fv0nlydz8o",
    "app_role": "Официант",
    "fio": "Бекзат Тузелов",
    "main_role_code": "PoV"
  },
  {
    "user_id": 1264,
    "login": "beksultan.alikulov",
    "password": "jdvhwklctc",
    "app_role": "Официант",
    "fio": "Бексултан Аликулов",
    "main_role_code": "PoV"
  },
  {
    "user_id": 1095,
    "login": "bibarys.spabek",
    "password": "hcsda22gvu",
    "app_role": "Официант",
    "fio": "Бибарыс Спабек",
    "main_role_code": "PoV"
  },
  {
    "user_id": 1096,
    "login": "bibigul.matishova",
    "password": "hl61mda2xp",
    "app_role": "Официант",
    "fio": "Бибигуль Матишова",
    "main_role_code": "WR1"
  },
  {
    "user_id": 1097,
    "login": "bota.abilkhayrova",
    "password": "hycb4s62em",
    "app_role": "Официант",
    "fio": "Бота Абилхайрова",
    "main_role_code": "WR1"
  },
  {
    "user_id": 1098,
    "login": "bota.azatkyzy",
    "password": "mp9203zvc3",
    "app_role": "Официант",
    "fio": "Бота Азаткызы",
    "main_role_code": "WR1"
  },
  {
    "user_id": 1099,
    "login": "botagoz.zhamalieva",
    "password": "vrsqc61xpg",
    "app_role": "Официант",
    "fio": "Ботагоз Жамалиева",
    "main_role_code": "PoV"
  },
  {
    "user_id": 1245,
    "login": "valeriy.ilin",
    "password": "5tok5jgnps",
    "app_role": "Официант",
    "fio": "Валерий Ильин",
    "main_role_code": "Sous chef"
  },
  {
    "user_id": 1100,
    "login": "galym.saparov",
    "password": "69lu4nv49z",
    "app_role": "Официант",
    "fio": "Галым Сапаров",
    "main_role_code": "PoV"
  },
  {
    "user_id": 1267,
    "login": "galym.saparov2",
    "password": "z5jgcx4mpo",
    "app_role": "Официант",
    "fio": "Галым Сапаров",
    "main_role_code": "PoV"
  },
  {
    "user_id": 1101,
    "login": "gaukhar.akbaeva",
    "password": "u7cn1vn5p7",
    "app_role": "Официант",
    "fio": "Гаухар Акбаева",
    "main_role_code": "Rec"
  },
  {
    "user_id": 1102,
    "login": "gaukhar.anarbaeva",
    "password": "g6ddamtyrd",
    "app_role": "Официант",
    "fio": "Гаухар Анарбаева",
    "main_role_code": "TehPer"
  },
  {
    "user_id": 1103,
    "login": "gleb.kuznetsov",
    "password": "kdnlzc5w4h",
    "app_role": "Официант",
    "fio": "Глеб Кузнецов",
    "main_role_code": "WR1"
  },
  {
    "user_id": 1104,
    "login": "guzal.kaimova",
    "password": "mwu9pxxrws",
    "app_role": "Официант",
    "fio": "Гузал Каимова",
    "main_role_code": "Sous chef"
  },
  {
    "user_id": 1105,
    "login": "gulzhan.mustafaeva",
    "password": "c7omnxh4gi",
    "app_role": "Официант",
    "fio": "Гульжан Мустафаева",
    "main_role_code": "Lepka"
  },
  {
    "user_id": 1272,
    "login": "gulmira.zhusupova",
    "password": "rjaahl35w0",
    "app_role": "Официант",
    "fio": "Гульмира Жусупова",
    "main_role_code": "ZavPr"
  },
  {
    "user_id": 1106,
    "login": "gulnaz.alieva",
    "password": "emjoi2maug",
    "app_role": "Официант",
    "fio": "Гульназ Алиева",
    "main_role_code": "PoV"
  },
  {
    "user_id": 1107,
    "login": "gulnaz.sayttsen",
    "password": "39skdytj68",
    "app_role": "Официант",
    "fio": "Гульназ Сайтцен",
    "main_role_code": "WR1"
  },
  {
    "user_id": 1108,
    "login": "dadash",
    "password": "aq467hz9yo",
    "app_role": "Официант",
    "fio": "Дадаш",
    "main_role_code": "WR1"
  },
  {
    "user_id": 1109,
    "login": "damir.irzhanov",
    "password": "m4ibvdkqfd",
    "app_role": "Официант",
    "fio": "Дамир Иржанов",
    "main_role_code": "BR1"
  },
  {
    "user_id": 1110,
    "login": "damir.khasenov",
    "password": "h6jl7lahub",
    "app_role": "Официант",
    "fio": "Дамир Хасенов",
    "main_role_code": "WR1"
  },
  {
    "user_id": 1111,
    "login": "dana.altaeva",
    "password": "fdsux11j5f",
    "app_role": "Официант",
    "fio": "Дана Алтаева",
    "main_role_code": "PoV"
  },
  {
    "user_id": 1112,
    "login": "dana.baltabaeva",
    "password": "h7rmqh59y1",
    "app_role": "Официант",
    "fio": "Дана Балтабаева",
    "main_role_code": "HolCeh"
  },
  {
    "user_id": 1113,
    "login": "dana.zhursinova",
    "password": "0lknli85wk",
    "app_role": "Официант",
    "fio": "Дана Журсинова",
    "main_role_code": "HolCeh"
  },
  {
    "user_id": 1114,
    "login": "danial.beybit",
    "password": "4kff2q6tc3",
    "app_role": "Официант",
    "fio": "Даниал Бейбит",
    "main_role_code": "HolCeh"
  },
  {
    "user_id": 1115,
    "login": "daniyar.dyusupov",
    "password": "b2fyphgw8s",
    "app_role": "Официант",
    "fio": "Данияр Дюсупов",
    "main_role_code": "Testo"
  },
  {
    "user_id": 1116,
    "login": "darkhan.azhikhanov",
    "password": "h7i2svs0z8",
    "app_role": "Официант",
    "fio": "Дархан Ажиханов",
    "main_role_code": "BR1"
  },
  {
    "user_id": 1253,
    "login": "daulet.maulitbekov",
    "password": "dtb77vl33u",
    "app_role": "Официант",
    "fio": "Даулет Мәулітбеков",
    "main_role_code": "PoV"
  },
  {
    "user_id": 1265,
    "login": "didar.orynbasar",
    "password": "9x353e9lnf",
    "app_role": "Официант",
    "fio": "Дидар Орынбасар",
    "main_role_code": "PoV"
  },
  {
    "user_id": 1118,
    "login": "dilnaz.rakhimgalieva",
    "password": "hnfd49mxo8",
    "app_role": "Официант",
    "fio": "Дильназ Рахимгалиева",
    "main_role_code": "WR1"
  },
  {
    "user_id": 1119,
    "login": "dinara.shakirova",
    "password": "ven3dcrujg",
    "app_role": "Официант",
    "fio": "Динара Шакирова",
    "main_role_code": "Lepka"
  },
  {
    "user_id": 1120,
    "login": "dinmukhamed.rzakhan",
    "password": "gh19hnmnns",
    "app_role": "Официант",
    "fio": "Динмухамед Рзахан",
    "main_role_code": "PoV"
  },
  {
    "user_id": 1121,
    "login": "dinmukhamet.akhmet",
    "password": "2b82bss9st",
    "app_role": "Официант",
    "fio": "Динмухамет Ахмет",
    "main_role_code": "MN1"
  },
  {
    "user_id": 1122,
    "login": "diyarbek.abdugafurov",
    "password": "fd9aegzbw4",
    "app_role": "Официант",
    "fio": "Диярбек Абдугафуров",
    "main_role_code": "WR1"
  },
  {
    "user_id": 1123,
    "login": "duysen.oralgan",
    "password": "0d8ehpalgu",
    "app_role": "Официант",
    "fio": "Дуйсен Оралган",
    "main_role_code": "PoV"
  },
  {
    "user_id": 1124,
    "login": "dulat.kamshybekov",
    "password": "uzkj83zcd5",
    "app_role": "Официант",
    "fio": "Дулат Камшыбеков",
    "main_role_code": "MN1"
  },
  {
    "user_id": 1255,
    "login": "dinnaz.armanqyzy2",
    "password": "y8a45sz615",
    "app_role": "Официант",
    "fio": "Дінназ Арманқызы",
    "main_role_code": "WR1"
  },
  {
    "user_id": 1261,
    "login": "dinnaz.armanqyzy",
    "password": "16t8nyq3hv",
    "app_role": "Официант",
    "fio": "Дінназ Арманқызы",
    "main_role_code": "WR1"
  },
  {
    "user_id": 1126,
    "login": "elena.savrambekova",
    "password": "rec743kr2f",
    "app_role": "Официант",
    "fio": "Елена Саврамбекова",
    "main_role_code": "PoV"
  },
  {
    "user_id": 1127,
    "login": "erasyl.orazali",
    "password": "5usbo13bvg",
    "app_role": "Официант",
    "fio": "Ерасыл Оразали",
    "main_role_code": "GC"
  },
  {
    "user_id": 1275,
    "login": "erasyl.qayyrden",
    "password": "bxpc19mczn",
    "app_role": "Официант",
    "fio": "Ерасыл Қайырден",
    "main_role_code": "WR1"
  },
  {
    "user_id": 1128,
    "login": "erbolat.abulkair",
    "password": "5i79yxt2p3",
    "app_role": "Официант",
    "fio": "Ерболат Абулкаир",
    "main_role_code": "WR1"
  },
  {
    "user_id": 1131,
    "login": "ertas.saginbek",
    "password": "w8hh6852t9",
    "app_role": "Официант",
    "fio": "Ертас Сагинбек",
    "main_role_code": "WR1"
  },
  {
    "user_id": 1132,
    "login": "eradil.erezhep",
    "password": "rbyjefplp1",
    "app_role": "Официант",
    "fio": "Ерәділ Ережеп",
    "main_role_code": "GorCeh"
  },
  {
    "user_id": 1134,
    "login": "zhandos.zhaqsyghaliev",
    "password": "ei5cwg0zac",
    "app_role": "Официант",
    "fio": "Жандос Жақсығалиев",
    "main_role_code": "PoV"
  },
  {
    "user_id": 1135,
    "login": "zhandos.shaymuratov",
    "password": "vd00p24i2e",
    "app_role": "Официант",
    "fio": "Жандос Шаймуратов",
    "main_role_code": "PoV"
  },
  {
    "user_id": 1136,
    "login": "zhanerke.baysupieva",
    "password": "w9pkgjnjo2",
    "app_role": "Официант",
    "fio": "Жанерке Байсупиева",
    "main_role_code": "MN1"
  },
  {
    "user_id": 1137,
    "login": "zhanna.mirzaeva",
    "password": "nn9j8hrhqi",
    "app_role": "Официант",
    "fio": "Жанна Мирзаева",
    "main_role_code": "PoV"
  },
  {
    "user_id": 1138,
    "login": "zhansulu.mukan",
    "password": "80w6mltsom",
    "app_role": "Официант",
    "fio": "Жансулу Мукан",
    "main_role_code": "WR1"
  },
  {
    "user_id": 1139,
    "login": "zhantemir.sultangaziev",
    "password": "34zqdas56c",
    "app_role": "Официант",
    "fio": "Жантемир Султангазиев",
    "main_role_code": "BR1"
  },
  {
    "user_id": 1140,
    "login": "zhasmin.amangeldieva",
    "password": "m94vfwf6se",
    "app_role": "Официант",
    "fio": "Жасмин Амангельдиева",
    "main_role_code": "WR1"
  },
  {
    "user_id": 1141,
    "login": "zhuldyz.baykadamova",
    "password": "417rhiwvni",
    "app_role": "Официант",
    "fio": "Жулдыз Байкадамова",
    "main_role_code": "PoV"
  },
  {
    "user_id": 1142,
    "login": "zalina.aytzhanova",
    "password": "mg2l3155z1",
    "app_role": "Официант",
    "fio": "Залина Айтжанова",
    "main_role_code": "STCalk"
  },
  {
    "user_id": 1143,
    "login": "zarina.mayyrova",
    "password": "zxdq6xmolf",
    "app_role": "Официант",
    "fio": "Зарина Майырова",
    "main_role_code": "MN1"
  },
  {
    "user_id": 1144,
    "login": "imambaeva.damele.zhanatovna",
    "password": "k0fskgtkwi",
    "app_role": "Официант",
    "fio": "Имамбаева Дамеле Жанатовна",
    "main_role_code": "WR1"
  },
  {
    "user_id": 1278,
    "login": "isa.aqylbek",
    "password": "xpm9o3atxo",
    "app_role": "Официант",
    "fio": "Иса Ақылбек",
    "main_role_code": "BR1"
  },
  {
    "user_id": 1146,
    "login": "isabek.ali",
    "password": "cuq2eo0oqo",
    "app_role": "Официант",
    "fio": "Исабек Али",
    "main_role_code": "PoV"
  },
  {
    "user_id": 1147,
    "login": "islam.bimulda",
    "password": "1opxtj6yxa",
    "app_role": "Официант",
    "fio": "Ислам Бимульда",
    "main_role_code": "Fas"
  },
  {
    "user_id": 1148,
    "login": "isroil.abdulloev",
    "password": "hzc7sant6l",
    "app_role": "Официант",
    "fio": "Исроил Абдуллоев",
    "main_role_code": "Фасовщик"
  },
  {
    "user_id": 1247,
    "login": "kairzhan.mukuev",
    "password": "dhfdapt292",
    "app_role": "Официант",
    "fio": "Каиржан Мукуев",
    "main_role_code": "Sous chef"
  },
  {
    "user_id": 1268,
    "login": "kaysar.osipov",
    "password": "eb1wtxutgs",
    "app_role": "Официант",
    "fio": "Кайсар Осипов",
    "main_role_code": "PoV"
  },
  {
    "user_id": 1276,
    "login": "kamila.zhagiparova",
    "password": "77wa1vfywd",
    "app_role": "Официант",
    "fio": "Камила Жагипарова",
    "main_role_code": "WR1"
  },
  {
    "user_id": 1149,
    "login": "konstantin.genze",
    "password": "hfhu1x3l6n",
    "app_role": "Официант",
    "fio": "Константин Гензе",
    "main_role_code": "WR1"
  },
  {
    "user_id": 1150,
    "login": "kristina.nosova",
    "password": "ugvl7ephkq",
    "app_role": "Официант",
    "fio": "Кристина Носова",
    "main_role_code": "PoV"
  },
  {
    "user_id": 1151,
    "login": "magzhan.dias.malikuly",
    "password": "fqp9l8xz9m",
    "app_role": "Официант",
    "fio": "Магжан Диас Маликулы",
    "main_role_code": "WR1"
  },
  {
    "user_id": 1152,
    "login": "madi.imanaliev",
    "password": "younuw77sv",
    "app_role": "Официант",
    "fio": "Мади Иманалиев",
    "main_role_code": "BR1"
  },
  {
    "user_id": 1153,
    "login": "madibek.makpal.su.shef",
    "password": "rbf5si9c7l",
    "app_role": "Официант",
    "fio": "Мадибек Макпал Су шеф",
    "main_role_code": "Sous chef"
  },
  {
    "user_id": 1154,
    "login": "madiyar.kasenov",
    "password": "hogbzugpeh",
    "app_role": "Официант",
    "fio": "Мадияр Касенов",
    "main_role_code": "BR1"
  },
  {
    "user_id": 1155,
    "login": "makpal.madibek",
    "password": "776r722klm",
    "app_role": "Официант",
    "fio": "Макпал Мадибек",
    "main_role_code": "PoV"
  },
  {
    "user_id": 1157,
    "login": "malikov.azamat",
    "password": "8ki0mf8179",
    "app_role": "Официант",
    "fio": "Маликов Азамат",
    "main_role_code": "WR1"
  },
  {
    "user_id": 1158,
    "login": "manas.seysenbaev.birzhanuly",
    "password": "wth17kh75z",
    "app_role": "Официант",
    "fio": "Манас Сейсенбаев Биржанулы",
    "main_role_code": "BR1"
  },
  {
    "user_id": 1159,
    "login": "marzhan.ismail",
    "password": "n8ojno9t5e",
    "app_role": "Официант",
    "fio": "Маржан Исмаил",
    "main_role_code": "Sous chef"
  },
  {
    "user_id": 1160,
    "login": "marzhan.serghazyqyzy",
    "password": "9k41mfmf1z",
    "app_role": "Официант",
    "fio": "Маржан Серғазықызы",
    "main_role_code": "WR1"
  },
  {
    "user_id": 1161,
    "login": "marina.sushko",
    "password": "8uul8m60l7",
    "app_role": "Официант",
    "fio": "Марина Сушко",
    "main_role_code": "Lepka"
  },
  {
    "user_id": 1162,
    "login": "mark.pivtsaev",
    "password": "7ebjf4umzh",
    "app_role": "Официант",
    "fio": "Марк Пивцаев",
    "main_role_code": "E com"
  },
  {
    "user_id": 1163,
    "login": "menkhatov.zhiger",
    "password": "6vjipnah53",
    "app_role": "Официант",
    "fio": "Менхатов Жигер",
    "main_role_code": "WR1"
  },
  {
    "user_id": 1164,
    "login": "meruert.galimova",
    "password": "91z113c5j8",
    "app_role": "Официант",
    "fio": "Меруерт Галимова",
    "main_role_code": "HR"
  },
  {
    "user_id": 1166,
    "login": "milena.marketolog",
    "password": "kp0961nqjy",
    "app_role": "Официант",
    "fio": "Милена Маркетолог",
    "main_role_code": "Mark"
  },
  {
    "user_id": 1167,
    "login": "muslim.khamzin",
    "password": "7m7fewzmfl",
    "app_role": "Официант",
    "fio": "Муслим Хамзин",
    "main_role_code": "MN1"
  },
  {
    "user_id": 1168,
    "login": "mukhametzhan.baytakov",
    "password": "d29qwp8zrh",
    "app_role": "Официант",
    "fio": "Мухаметжан Байтаков",
    "main_role_code": "Sous chef"
  },
  {
    "user_id": 1169,
    "login": "myrzabek.abdigani",
    "password": "l5ivzsrr2k",
    "app_role": "Официант",
    "fio": "Мырзабек Абдигани",
    "main_role_code": "WR1"
  },
  {
    "user_id": 1170,
    "login": "navruzbek.shomurodov",
    "password": "o4uoitxioh",
    "app_role": "Официант",
    "fio": "Наврузбек Шомуродов",
    "main_role_code": "PoV"
  },
  {
    "user_id": 1171,
    "login": "nazgul.erkingalieva",
    "password": "8b08ftglhd",
    "app_role": "Официант",
    "fio": "Назгул Еркингалиева",
    "main_role_code": "Calc"
  },
  {
    "user_id": 1172,
    "login": "nazira.amangeldieva",
    "password": "5vgea9xlyc",
    "app_role": "Официант",
    "fio": "Назира Амангельдиева",
    "main_role_code": "HolCeh"
  },
  {
    "user_id": 1173,
    "login": "nurasyl.tagaybay",
    "password": "kptlm6ba46",
    "app_role": "Официант",
    "fio": "Нурасыл Тагайбай",
    "main_role_code": "PoV"
  },
  {
    "user_id": 1174,
    "login": "nurbolat.eshtaev",
    "password": "db4taqbliu",
    "app_role": "Официант",
    "fio": "Нурболат Ештаев",
    "main_role_code": "Testo"
  },
  {
    "user_id": 1175,
    "login": "nurbolat.serikbay",
    "password": "dpxqjjl51n",
    "app_role": "Официант",
    "fio": "Нурболат Серикбай",
    "main_role_code": "BR1"
  },
  {
    "user_id": 1176,
    "login": "nurgisa.abduali",
    "password": "ocmo8yzekq",
    "app_role": "Официант",
    "fio": "Нургиса Абдуали",
    "main_role_code": "PoV"
  },
  {
    "user_id": 1177,
    "login": "nurgisa.kerimbekov",
    "password": "928b6tda4l",
    "app_role": "Официант",
    "fio": "Нургиса Керимбеков",
    "main_role_code": "PoV"
  },
  {
    "user_id": 1178,
    "login": "nurdaulet.orak",
    "password": "x1wj9e6nzd",
    "app_role": "Официант",
    "fio": "Нурдаулет Орак",
    "main_role_code": "WR1"
  },
  {
    "user_id": 1179,
    "login": "nurzhamal.bilimbetova",
    "password": "5dgyjc5c1u",
    "app_role": "Официант",
    "fio": "Нуржамал Билимбетова",
    "main_role_code": "PoV"
  },
  {
    "user_id": 1180,
    "login": "nurzhan.shaymerdenov",
    "password": "18gbryfog6",
    "app_role": "Официант",
    "fio": "Нуржан Шаймерденов",
    "main_role_code": "Testo"
  },
  {
    "user_id": 1181,
    "login": "nurmukhanov.temirbek",
    "password": "j5o6ji50fk",
    "app_role": "Официант",
    "fio": "Нурмуханов Темирбек",
    "main_role_code": "WR1"
  },
  {
    "user_id": 1182,
    "login": "nursultan.toylybaev",
    "password": "9gol7zg555",
    "app_role": "Официант",
    "fio": "Нурсултан Тойлыбаев",
    "main_role_code": "BR1"
  },
  {
    "user_id": 1183,
    "login": "olesya",
    "password": "kwfrutdrcw",
    "app_role": "Официант",
    "fio": "Олеся",
    "main_role_code": "STCalk"
  },
  {
    "user_id": 1248,
    "login": "olzhas.muratov",
    "password": "0we2iwq9il",
    "app_role": "Официант",
    "fio": "Олжас Муратов",
    "main_role_code": "PoV"
  },
  {
    "user_id": 1184,
    "login": "omarbek.kenzhegali",
    "password": "pe542pvpcq",
    "app_role": "Официант",
    "fio": "Омарбек Кенжегали",
    "main_role_code": "BR1"
  },
  {
    "user_id": 1185,
    "login": "orazbekov.asylkhan",
    "password": "1ib2lv7811",
    "app_role": "Официант",
    "fio": "Оразбеков Асылхан",
    "main_role_code": "WR1"
  },
  {
    "user_id": 1186,
    "login": "oral.zhetbyspaeva",
    "password": "ffeo97koic",
    "app_role": "Официант",
    "fio": "Орал Жетбыспаева",
    "main_role_code": "TehPer"
  },
  {
    "user_id": 1187,
    "login": "oralkhan.parmanov",
    "password": "jaj0j6fg9b",
    "app_role": "Официант",
    "fio": "Оралхан Парманов",
    "main_role_code": "PoV"
  },
  {
    "user_id": 1188,
    "login": "orzu.kambarov",
    "password": "6yur7skee3",
    "app_role": "Официант",
    "fio": "Орзу Камбаров",
    "main_role_code": "WR1"
  },
  {
    "user_id": 1189,
    "login": "otabek.atakullaev",
    "password": "rr5jrxkh1f",
    "app_role": "Официант",
    "fio": "Отабек Атакуллаев",
    "main_role_code": "Fas"
  },
  {
    "user_id": 1198,
    "login": "rabiga.beksugurova",
    "password": "v8swglmvyv",
    "app_role": "Официант",
    "fio": "Рабига Бексугурова",
    "main_role_code": "Testo"
  },
  {
    "user_id": 1199,
    "login": "ramazan.umirzakov",
    "password": "xmdqw8hvxv",
    "app_role": "Официант",
    "fio": "Рамазан Умирзаков",
    "main_role_code": "PoV"
  },
  {
    "user_id": 1200,
    "login": "rakhat.kabdrash",
    "password": "9ay686i0jr",
    "app_role": "Официант",
    "fio": "Рахат Кабдраш",
    "main_role_code": "WR1"
  },
  {
    "user_id": 1201,
    "login": "rinat.kulzhabay.galymzhanuly",
    "password": "tc1b8ttrsh",
    "app_role": "Официант",
    "fio": "Ринат Кулжабай Галымжанулы",
    "main_role_code": "WR1"
  },
  {
    "user_id": 1266,
    "login": "ruslan.apenov",
    "password": "h5eave72ta",
    "app_role": "Официант",
    "fio": "Руслан Апенов",
    "main_role_code": "PoV"
  },
  {
    "user_id": 1203,
    "login": "rustem.kanaev",
    "password": "zv2ijiqmhl",
    "app_role": "Официант",
    "fio": "Рустем Канаев",
    "main_role_code": "WR1"
  },
  {
    "user_id": 1256,
    "login": "rustem.ramankulov",
    "password": "zh628zn4yi",
    "app_role": "Официант",
    "fio": "Рустем Раманкулов",
    "main_role_code": "PoV"
  },
  {
    "user_id": 1204,
    "login": "sabit.mukanov",
    "password": "b30ewogmvv",
    "app_role": "Официант",
    "fio": "Сабит Муканов",
    "main_role_code": "PoV"
  },
  {
    "user_id": 1205,
    "login": "sabyrzhan.sadykov",
    "password": "04yr4kp1gj",
    "app_role": "Официант",
    "fio": "Сабыржан Садыков",
    "main_role_code": "BR1"
  },
  {
    "user_id": 1206,
    "login": "saltanat.nurabaeva",
    "password": "tgto5hb1l1",
    "app_role": "Официант",
    "fio": "Салтанат Нурабаева",
    "main_role_code": "Sous chef"
  },
  {
    "user_id": 1207,
    "login": "sayan.berkinbay",
    "password": "re99ig02oo",
    "app_role": "Официант",
    "fio": "Саян Беркінбай",
    "main_role_code": "PoV"
  },
  {
    "user_id": 1208,
    "login": "svetlana.goeva",
    "password": "zvfp6rom6e",
    "app_role": "Официант",
    "fio": "Светлана Гоева",
    "main_role_code": "OpDir"
  },
  {
    "user_id": 1209,
    "login": "sergey.ligay",
    "password": "wy6iam2c77",
    "app_role": "Официант",
    "fio": "Сергей Лигай",
    "main_role_code": "Аудитор"
  },
  {
    "user_id": 1210,
    "login": "serzhan.tileubergen",
    "password": "nka6x51hng",
    "app_role": "Официант",
    "fio": "Сержан Тилеуберген",
    "main_role_code": "WR1"
  },
  {
    "user_id": 1259,
    "login": "serik.azamat",
    "password": "incbrhgm66",
    "app_role": "Официант",
    "fio": "Серик Азамат",
    "main_role_code": "WR1"
  },
  {
    "user_id": 1211,
    "login": "serik.akzhigitov",
    "password": "rikvn39l4q",
    "app_role": "Официант",
    "fio": "Серик Акжигитов",
    "main_role_code": "SBr"
  },
  {
    "user_id": 1213,
    "login": "starter",
    "password": "dfc000asx3",
    "app_role": "Официант",
    "fio": "Стартер",
    "main_role_code": "KWAAKA"
  },
  {
    "user_id": 1214,
    "login": "sultan.shayken",
    "password": "bqtfyrjl3z",
    "app_role": "Официант",
    "fio": "Султан Шайкен",
    "main_role_code": "BR1"
  },
  {
    "user_id": 1215,
    "login": "tair.kazbek",
    "password": "haab9pnee7",
    "app_role": "Официант",
    "fio": "Таир Казбек",
    "main_role_code": "BR1"
  },
  {
    "user_id": 1216,
    "login": "talgat.moldakimov",
    "password": "xct3xrt1nw",
    "app_role": "Официант",
    "fio": "Талгат Молдакимов",
    "main_role_code": "PoV"
  },
  {
    "user_id": 1217,
    "login": "talgat.tyulebaev",
    "password": "la5q14zlwr",
    "app_role": "Официант",
    "fio": "Талгат Тюлебаев",
    "main_role_code": "Fas"
  },
  {
    "user_id": 1218,
    "login": "talgatbek.kazhdanbekov",
    "password": "ya115sv0zh",
    "app_role": "Официант",
    "fio": "Талгатбек Кажданбеков",
    "main_role_code": "PoV"
  },
  {
    "user_id": 1219,
    "login": "tamara.gergaya",
    "password": "poxa2wv2kr",
    "app_role": "Официант",
    "fio": "Тамара Гергая",
    "main_role_code": "PoV"
  },
  {
    "user_id": 1220,
    "login": "tamerlan.ryazantsev",
    "password": "o5gpis1rze",
    "app_role": "Официант",
    "fio": "Тамерлан Рязанцев",
    "main_role_code": "WR1"
  },
  {
    "user_id": 1221,
    "login": "tanat.zhapparkhan",
    "password": "fi88ahfoqa",
    "app_role": "Официант",
    "fio": "Танат Жаппархан",
    "main_role_code": "Sous chef"
  },
  {
    "user_id": 1222,
    "login": "tastemir.suleymanov",
    "password": "mxgjdwey4s",
    "app_role": "Официант",
    "fio": "Тастемир Сулейманов",
    "main_role_code": "BR1"
  },
  {
    "user_id": 1223,
    "login": "teymur.agalarov",
    "password": "aeabe77ogu",
    "app_role": "Официант",
    "fio": "Теймур Агаларов",
    "main_role_code": "WR1"
  },
  {
    "user_id": 1249,
    "login": "temirbek.ulykpanov",
    "password": "d7kyruc0p9",
    "app_role": "Официант",
    "fio": "Темирбек Улыкпанов",
    "main_role_code": "BR1"
  },
  {
    "user_id": 1270,
    "login": "temirlan.beysenov",
    "password": "3pqcw7k1n7",
    "app_role": "Официант",
    "fio": "Темирлан Бейсенов",
    "main_role_code": "Sous chef"
  },
  {
    "user_id": 1224,
    "login": "temirlan.saylau",
    "password": "v55sq4idvi",
    "app_role": "Официант",
    "fio": "Темирлан Сайлау",
    "main_role_code": "WR1"
  },
  {
    "user_id": 1225,
    "login": "temirkhanova.aliya",
    "password": "yd993yndk2",
    "app_role": "Официант",
    "fio": "Темирханова Алия",
    "main_role_code": "Rec"
  },
  {
    "user_id": 1260,
    "login": "temirkhan.saparkhan",
    "password": "95bfdgi1uw",
    "app_role": "Официант",
    "fio": "Темірхан Сапархан",
    "main_role_code": "PoV"
  },
  {
    "user_id": 1227,
    "login": "tleukhor.rakhmetova",
    "password": "zbqmmpbp2a",
    "app_role": "Официант",
    "fio": "Тлеухор Рахметова",
    "main_role_code": "Brig"
  },
  {
    "user_id": 1258,
    "login": "tulegen.amanzholov",
    "password": "lcdie6jo3y",
    "app_role": "Официант",
    "fio": "Тулеген Аманжолов",
    "main_role_code": "PoV"
  },
  {
    "user_id": 1229,
    "login": "turlybek.anuarbek",
    "password": "o5y8nyek10",
    "app_role": "Официант",
    "fio": "Турлыбек Ануарбек",
    "main_role_code": "WR1"
  },
  {
    "user_id": 1230,
    "login": "uayys.zholdas",
    "password": "kxtbnsufwz",
    "app_role": "Официант",
    "fio": "Уайыс Жолдас",
    "main_role_code": "BR1"
  },
  {
    "user_id": 1231,
    "login": "ulagat.serikbay",
    "password": "90d7ryfic6",
    "app_role": "Официант",
    "fio": "Улагат Серикбай",
    "main_role_code": "GorCeh"
  },
  {
    "user_id": 1262,
    "login": "ulan.zhanuzak",
    "password": "mojwhbjgme",
    "app_role": "Официант",
    "fio": "Улан Жанузак",
    "main_role_code": "E com"
  },
  {
    "user_id": 1232,
    "login": "ular.erkin",
    "password": "n4xyfccjps",
    "app_role": "Официант",
    "fio": "Улар Еркин",
    "main_role_code": "PoV"
  },
  {
    "user_id": 1254,
    "login": "umida.bektibaeva",
    "password": "vjgnoxpdbw",
    "app_role": "Официант",
    "fio": "Умида Бектибаева",
    "main_role_code": "PoV"
  },
  {
    "user_id": 1233,
    "login": "umirzhan.rakhimberdiev",
    "password": "vybnaabp42",
    "app_role": "Официант",
    "fio": "Умиржан Рахимбердиев",
    "main_role_code": "WR1"
  },
  {
    "user_id": 1234,
    "login": "urazalin.ruslan",
    "password": "me35ggd14c",
    "app_role": "Официант",
    "fio": "Уразалин Руслан",
    "main_role_code": "GorCeh"
  },
  {
    "user_id": 1235,
    "login": "faridin.nur.mokhammad",
    "password": "zu86f1p0ae",
    "app_role": "Официант",
    "fio": "Фаридин Нур Мохаммад",
    "main_role_code": "PCon"
  },
  {
    "user_id": 1236,
    "login": "feruza.sabikhanova",
    "password": "3ufqxzkjk7",
    "app_role": "Официант",
    "fio": "Феруза Сабиханова",
    "main_role_code": "PoV"
  },
  {
    "user_id": 1237,
    "login": "kholimdzhon.zaynidilov",
    "password": "4ojhl28fsm",
    "app_role": "Официант",
    "fio": "Холимджон Зайнидилов",
    "main_role_code": "Fas"
  },
  {
    "user_id": 1238,
    "login": "shakhriyar.matnyazov",
    "password": "edjc4o0gf7",
    "app_role": "Официант",
    "fio": "Шахрияр Матньязов",
    "main_role_code": "WR1"
  },
  {
    "user_id": 1239,
    "login": "sherkhan.nurtaza",
    "password": "p3sa0f32gy",
    "app_role": "Официант",
    "fio": "Шерхан Нұртаза",
    "main_role_code": "BR1"
  },
  {
    "user_id": 1240,
    "login": "shukrullo.nizomov",
    "password": "mpf96bxvvl",
    "app_role": "Официант",
    "fio": "Шукрулло Низомов",
    "main_role_code": "BR1"
  },
  {
    "user_id": 1241,
    "login": "shyntaeva.gulnara",
    "password": "36lglgmkra",
    "app_role": "Официант",
    "fio": "Шынтаева Гулнара",
    "main_role_code": "TehPer"
  },
  {
    "user_id": 1242,
    "login": "yana.dilman",
    "password": "malpbk2cu4",
    "app_role": "Официант",
    "fio": "Яна Дильман",
    "main_role_code": "BR1"
  },
  {
    "user_id": 1244,
    "login": "adilet.zheksenbek",
    "password": "9jxv9nrpex",
    "app_role": "Официант",
    "fio": "Әділет Жексенбек",
    "main_role_code": "BR1"
  }
]